nmk_badges/__init__.py
nmk_badges/badges.yml
nmk_badges/builder.py
nmk_badges/plugin.yml
nmk_badges-1.0.0.dist-info/LICENSE
nmk_badges-1.0.0.dist-info/METADATA
nmk_badges-1.0.0.dist-info/WHEEL
nmk_badges-1.0.0.dist-info/top_level.txt
nmk_badges-1.0.0.dist-info/RECORD
