Metadata-Version: 2.1
Name: nmk-badges
Version: 1.0.0
Summary: Readme badges generation plugin for nmk build system
Author: The dynod project
Maintainer: The dynod project
License: MIT License
Project-URL: Homepage, https://github.com/dynod/nmk-badges
Project-URL: Repository, https://github.com/dynod/nmk-badges
Project-URL: Issues, https://github.com/dynod/nmk/issues?q=is%3Aopen+is%3Aissue+label%3Aplugin%3Abadges
Classifier: Programming Language :: Python :: 3.9
Classifier: Programming Language :: Python :: 3.10
Classifier: Programming Language :: Python :: 3.11
Classifier: Programming Language :: Python :: 3.12
Classifier: Programming Language :: Python :: 3.13
Requires-Python: >=3.9
License-File: LICENSE
Requires-Dist: nmk-base
